uwhoisd/__init__.py
uwhoisd/_version.py
uwhoisd/caching.py
uwhoisd/client.py
uwhoisd/defaults.ini
uwhoisd/rl.py
uwhoisd/scraper.py
uwhoisd/server.py
uwhoisd/utils.py
uwhoisd-0.1.0.dist-info/METADATA
uwhoisd-0.1.0.dist-info/WHEEL
uwhoisd-0.1.0.dist-info/entry_points.txt
uwhoisd-0.1.0.dist-info/licenses/LICENSE
uwhoisd-0.1.0.dist-info/RECORD
