Metadata-Version: 2.3
Name: uwhoisd
Version: 0.1.0
Summary: Universal domain WHOIS proxy server
Project-URL: Documentation, https://github.com/kgaughan/uwhoisd#readme
Project-URL: Issues, https://github.com/kgaughan/uwhoisd/issues
Project-URL: Source, https://github.com/kgaughan/uwhoisd
Author-email: Keith Gaughan <k@stereochro.me>
License: MIT License
License-File: LICENSE
Classifier: Development Status :: 2 - Pre-Alpha
Classifier: Environment :: No Input/Output (Daemon)
Classifier: Intended Audience :: System Administrators
Classifier: License :: OSI Approved :: MIT License
Classifier: Operating System :: OS Independent
Classifier: Programming Language :: Python
Classifier: Programming Language :: Python :: 3.8
Classifier: Programming Language :: Python :: 3.9
Classifier: Programming Language :: Python :: 3.10
Classifier: Programming Language :: Python :: 3.11
Classifier: Programming Language :: Python :: Implementation :: CPython
Classifier: Programming Language :: Python :: Implementation :: PyPy
Classifier: Topic :: Internet
Classifier: Topic :: System :: Networking
Requires-Python: >=3.8
Requires-Dist: beautifulsoup4>=4.12.3
Requires-Dist: requests>=2.32.3
